smarthome_utils/U14Robot.py
smarthome_utils/U19Robot.py
smarthome_utils/__init__.py
smarthome_utils/smarthome_utils.py
smarthome_utils-0.0.4.dist-info/METADATA
smarthome_utils-0.0.4.dist-info/WHEEL
smarthome_utils-0.0.4.dist-info/licenses/LICENSE
smarthome_utils-0.0.4.dist-info/RECORD
