Metadata-Version: 2.4
Name: smarthome-utils
Version: 0.0.4
Summary: A starting package to work with smarthome robot
Project-URL: Homepage, https://github.com/fira-smarthome/smarthome-utils
Project-URL: Issues, https://github.com/fira-smarthome/smarthome-utils/issues
Author-email: Sina Zaker <cnazk98@gmail.com>
License-Expression: MIT
License-File: LICENSE
Classifier: Operating System :: OS Independent
Classifier: Programming Language :: Python :: 3
Requires-Python: >=3.9
